xkits_sheet/__init__.py
xkits_sheet/attribute.py
xkits_sheet/csv.py
xkits_sheet/table.py
xkits_sheet/xls.py
xkits_sheet/xlsx.py
xkits_sheet-0.1.dist-info/LICENSE
xkits_sheet-0.1.dist-info/METADATA
xkits_sheet-0.1.dist-info/WHEEL
xkits_sheet-0.1.dist-info/top_level.txt
xkits_sheet-0.1.dist-info/zip-safe
xkits_sheet-0.1.dist-info/RECORD
